mcpi-e/__init__.py
mcpi-e/block.py
mcpi-e/connection.py
mcpi-e/entity.py
mcpi-e/event.py
mcpi-e/minecraft.py
mcpi-e/util.py
mcpi-e/vec3.py
mcpi_e/BlockEnum.py
mcpi_e/__init__.py
mcpi_e/block.py
mcpi_e/connection.py
mcpi_e/drawing.py
mcpi_e/entity.py
mcpi_e/event.py
mcpi_e/logger.py
mcpi_e/minecraft.py
mcpi_e/settings.py
mcpi_e/util.py
mcpi_e/vec3.py
mcpi_e-0.3.2006.2.dist-info/LICENSE
mcpi_e-0.3.2006.2.dist-info/METADATA
mcpi_e-0.3.2006.2.dist-info/WHEEL
mcpi_e-0.3.2006.2.dist-info/top_level.txt
mcpi_e-0.3.2006.2.dist-info/RECORD
